mcmst_clust/__init__.py
mcmst_clust/core.py
mcmst_clust/utils.py
mcmst_clust-1.1.0.dist-info/METADATA
mcmst_clust-1.1.0.dist-info/WHEEL
mcmst_clust-1.1.0.dist-info/top_level.txt
mcmst_clust-1.1.0.dist-info/RECORD
