Metadata-Version: 2.4
Name: mcmst_clust
Version: 1.1.0
Summary: MCMSTClustering: Minimum Spanning Tree and Micro-Cluster based Clustering Algorithm
Home-page: https://github.com/yourusername/mcmstclustering
Author: Ali Senol
Author-email: Ali Şenol <alisenol@tarsus.edu.tr>
Project-URL: Homepage, https://github.com/senolali/MCMSTClustering
Project-URL: Documentation, https://github.com/senolali/MCMSTClustering
Project-URL: Paper, https://doi.org/10.1007/s00521-023-08386-3
Requires-Python: >=3.7
Requires-Dist: numpy
Requires-Dist: scipy
Requires-Dist: networkx
Dynamic: author
Dynamic: home-page
Dynamic: requires-python
